{
  "id": "c93f203e-ddc1-4bca-8c3a-e8cd768336ff",
  "prevId": "127d980b-c37b-4373-8c15-fa142a42ce8e",
  "version": "7",
  "dialect": "postgresql",
  "tables": {
    "public.lancamento": {
      "name": "lancamento",
      "schema": "",
      "columns": {
        "id": {
          "name": "id",
          "type": "serial",
          "primaryKey": true,
          "notNull": true
        },
        "descricao": {
          "name": "descricao",
          "type": "varchar(255)",
          "primaryKey": false,
          "notNull": true
        },
        "data_lancamento": {
          "name": "data_lancamento",
          "type": "date",
          "primaryKey": false,
          "notNull": true
        },
        "valor": {
          "name": "valor",
          "type": "numeric(12, 2)",
          "primaryKey": false,
          "notNull": true
        },
        "tipo_lancamento": {
          "name": "tipo_lancamento",
          "type": "varchar(20)",
          "primaryKey": false,
          "notNull": true
        },
        "situacao": {
          "name": "situacao",
          "type": "varchar(20)",
          "primaryKey": false,
          "notNull": true
        },
        "usuario_id": {
          "name": "usuario_id",
          "type": "integer",
          "primaryKey": false,
          "notNull": true
        },
        "add": {
          "name": "add",
          "type": "varchar(255)",
          "primaryKey": false,
          "notNull": false
        }
      },
      "indexes": {},
      "foreignKeys": {
        "lancamento_usuario_id_usuario_id_fk": {
          "name": "lancamento_usuario_id_usuario_id_fk",
          "tableFrom": "lancamento",
          "tableTo": "usuario",
          "columnsFrom": [
            "usuario_id"
          ],
          "columnsTo": [
            "id"
          ],
          "onDelete": "no action",
          "onUpdate": "no action"
        }
      },
      "compositePrimaryKeys": {},
      "uniqueConstraints": {},
      "policies": {},
      "checkConstraints": {},
      "isRLSEnabled": false
    },
    "public.usuario": {
      "name": "usuario",
      "schema": "",
      "columns": {
        "id": {
          "name": "id",
          "type": "serial",
          "primaryKey": true,
          "notNull": true
        },
        "nome": {
          "name": "nome",
          "type": "varchar(120)",
          "primaryKey": false,
          "notNull": true
        },
        "login": {
          "name": "login",
          "type": "varchar(80)",
          "primaryKey": false,
          "notNull": true
        },
        "senha": {
          "name": "senha",
          "type": "varchar(255)",
          "primaryKey": false,
          "notNull": true
        },
        "situacao": {
          "name": "situacao",
          "type": "varchar(20)",
          "primaryKey": false,
          "notNull": true
        }
      },
      "indexes": {},
      "foreignKeys": {},
      "compositePrimaryKeys": {},
      "uniqueConstraints": {
        "usuario_login_unique": {
          "name": "usuario_login_unique",
          "nullsNotDistinct": false,
          "columns": [
            "login"
          ]
        }
      },
      "policies": {},
      "checkConstraints": {},
      "isRLSEnabled": false
    }
  },
  "enums": {},
  "schemas": {},
  "sequences": {},
  "roles": {},
  "policies": {},
  "views": {},
  "_meta": {
    "columns": {},
    "schemas": {},
    "tables": {}
  }
}